{
  "openapi": "3.0.3",
  "info": {
    "title": "EPA CapabilityStatement für den Patient Service",
    "version": "1.1.5",
    "description": "EPA CapabilityStatement für den Patient Service"
  },
  "paths": {
    "/Patient": {
      "get": {
        "summary": "Search for Patient",
        "tags": [
          "Patient"
        ],
        "parameters": [
          {
            "name": "X-Request-ID",
            "in": "header",
            "required": true,
            "description": "UUID of the request message",
            "schema": {
              "type": "string",
              "format": "uuid"
            }
          },
          {
            "name": "x-insurantid",
            "in": "header",
            "required": true,
            "description": "Health Record Identifier",
            "schema": {
              "type": "string",
              "pattern": "^[A-Z]{1}\\d{9}$"
            }
          },
          {
            "name": "x-useragent",
            "in": "header",
            "required": true,
            "description": "user agent information",
            "schema": {
              "type": "string",
              "pattern": "^[a-zA-Z0-9]{20}\\/[a-zA-Z0-9\\-\\.]{1,15}$"
            }
          },
          {
            "name": "_format",
            "in": "query",
            "required": false,
            "description": "Specifies the return format",
            "schema": {
              "type": "string",
              "enum": [
                "application/fhir+json",
                "application/fhir+xml"
              ]
            }
          },
          {
            "name": "_count",
            "in": "query",
            "required": false,
            "description": "With _count, the client can specify the maximum number of elements to be included on one page of the response. This means the Medication Service limits the result set to this maximum specified number. If no value for _count is provided, the default value set is 25.",
            "schema": {
              "type": "string"
            }
          },
          {
            "name": "_offset",
            "in": "query",
            "required": false,
            "description": "This URL parameter indicates the (zero-based) offset of the first returned element in the collection. If no value for _offset is provided, the default value set is 0.",
            "schema": {
              "type": "integer"
            }
          },
          {
            "name": "_total",
            "in": "query",
            "required": false,
            "description": "This parameter controls whether and how the AuditEvent Service returns the total number of search results.",
            "schema": {
              "type": "string"
            }
          },
          {
            "name": "identifier",
            "in": "query",
            "required": false,
            "schema": {
              "type": "string"
            },
            "description": "Patient.identifier"
          }
        ],
        "responses": {
          "200": {
            "description": "Search successful",
            "content": {
              "application/fhir+json": {
                "schema": {
                  "type": "object"
                }
              },
              "application/fhir+xml": {
                "schema": {
                  "type": "object"
                }
              }
            }
          },
          "400": {
            "description": "Invalid request"
          },
          "404": {
            "description": "Health record is in state UNKNOWN or INITIALIZED"
          },
          "403": {
            "description": "Device registration does not exist"
          },
          "409": {
            "description": "Health record is in state SUSPENDED"
          },
          "500": {
            "description": "Any other error"
          }
        }
      }
    },
    "/Patient/{id}": {
      "get": {
        "summary": "Read a specific Patient",
        "tags": [
          "Patient"
        ],
        "parameters": [
          {
            "name": "X-Request-ID",
            "in": "header",
            "required": true,
            "description": "UUID of the request message",
            "schema": {
              "type": "string",
              "format": "uuid"
            }
          },
          {
            "name": "x-insurantid",
            "in": "header",
            "required": true,
            "description": "Health Record Identifier",
            "schema": {
              "type": "string",
              "pattern": "^[A-Z]{1}\\d{9}$"
            }
          },
          {
            "name": "x-useragent",
            "in": "header",
            "required": true,
            "description": "user agent information",
            "schema": {
              "type": "string",
              "pattern": "^[a-zA-Z0-9]{20}\\/[a-zA-Z0-9\\-\\.]{1,15}$"
            }
          },
          {
            "name": "id",
            "in": "path",
            "required": true,
            "schema": {
              "type": "string"
            },
            "description": "Resource ID"
          },
          {
            "name": "_format",
            "in": "query",
            "required": false,
            "description": "Specifies the return format",
            "schema": {
              "type": "string",
              "enum": [
                "application/fhir+json",
                "application/fhir+xml"
              ]
            }
          }
        ],
        "responses": {
          "200": {
            "description": "Patient successfully read",
            "content": {
              "application/fhir+json": {
                "schema": {
                  "type": "object"
                }
              },
              "application/fhir+xml": {
                "schema": {
                  "type": "object"
                }
              }
            }
          },
          "400": {
            "description": "Invalid request"
          },
          "404": {
            "description": "Health record is in state UNKNOWN or INITIALIZED"
          },
          "403": {
            "description": "Device registration does not exist"
          },
          "409": {
            "description": "Health record is in state SUSPENDED"
          },
          "500": {
            "description": "Any other error"
          }
        }
      },
      "put": {
        "summary": "Update Patient by ID",
        "tags": [
          "Patient"
        ],
        "parameters": [
          {
            "name": "X-Request-ID",
            "in": "header",
            "required": true,
            "description": "UUID of the request message",
            "schema": {
              "type": "string",
              "format": "uuid"
            }
          },
          {
            "name": "x-insurantid",
            "in": "header",
            "required": true,
            "description": "Health Record Identifier",
            "schema": {
              "type": "string",
              "pattern": "^[A-Z]{1}\\d{9}$"
            }
          },
          {
            "name": "x-useragent",
            "in": "header",
            "required": true,
            "description": "user agent information",
            "schema": {
              "type": "string",
              "pattern": "^[a-zA-Z0-9]{20}\\/[a-zA-Z0-9\\-\\.]{1,15}$"
            }
          },
          {
            "name": "id",
            "in": "path",
            "required": true,
            "schema": {
              "type": "string"
            },
            "description": "Resource ID"
          }
        ],
        "responses": {
          "200": {
            "description": "Resource updated",
            "content": {
              "application/fhir+json": {
                "schema": {
                  "type": "object"
                }
              },
              "application/fhir+xml": {
                "schema": {
                  "type": "object"
                }
              }
            }
          },
          "201": {
            "description": "Created, wenn eine neue Ressourceninstanz erstellt wurde"
          },
          "400": {
            "description": "Bad Request, falls eine falsche ID in der Anfrage angegeben wurde"
          },
          "403": {
            "description": "Device registration does not exist"
          },
          "404": {
            "description": "Health record is in state UNKNOWN or INITIALIZED"
          },
          "412": {
            "description": "Precondition Failed, wenn mehrere Ressourceninstanz gefunden wurden"
          },
          "409": {
            "description": "Health record is in state SUSPENDED"
          },
          "500": {
            "description": "Any other error"
          }
        },
        "requestBody": {
          "required": true,
          "content": {
            "application/fhir+json": {
              "schema": {
                "type": "object"
              }
            },
            "application/fhir+xml": {
              "schema": {
                "type": "object"
              }
            }
          }
        }
      }
    },
    "/Patient/{id}/_history/{vid}": {
      "get": {
        "summary": "Read version of Patient",
        "tags": [
          "Patient"
        ],
        "parameters": [
          {
            "name": "X-Request-ID",
            "in": "header",
            "required": true,
            "description": "UUID of the request message",
            "schema": {
              "type": "string",
              "format": "uuid"
            }
          },
          {
            "name": "x-insurantid",
            "in": "header",
            "required": true,
            "description": "Health Record Identifier",
            "schema": {
              "type": "string",
              "pattern": "^[A-Z]{1}\\d{9}$"
            }
          },
          {
            "name": "x-useragent",
            "in": "header",
            "required": true,
            "description": "user agent information",
            "schema": {
              "type": "string",
              "pattern": "^[a-zA-Z0-9]{20}\\/[a-zA-Z0-9\\-\\.]{1,15}$"
            }
          },
          {
            "name": "id",
            "in": "path",
            "required": true,
            "schema": {
              "type": "string"
            },
            "description": "Resource ID"
          },
          {
            "name": "vid",
            "in": "path",
            "required": true,
            "schema": {
              "type": "string"
            },
            "description": "Version ID"
          },
          {
            "name": "_format",
            "in": "query",
            "required": false,
            "description": "Specifies the return format",
            "schema": {
              "type": "string",
              "enum": [
                "application/fhir+json",
                "application/fhir+xml"
              ]
            }
          }
        ],
        "responses": {
          "200": {
            "description": "Patient version read",
            "content": {
              "application/fhir+json": {
                "schema": {
                  "type": "object"
                }
              },
              "application/fhir+xml": {
                "schema": {
                  "type": "object"
                }
              }
            }
          },
          "400": {
            "description": "Invalid request"
          },
          "404": {
            "description": "Health record is in state UNKNOWN or INITIALIZED"
          },
          "403": {
            "description": "Device registration does not exist"
          },
          "409": {
            "description": "Health record is in state SUSPENDED"
          },
          "500": {
            "description": "Any other error"
          }
        }
      }
    },
    "/Patient/{id}/_history": {
      "get": {
        "summary": "History of a specific Patient",
        "tags": [
          "Patient"
        ],
        "parameters": [
          {
            "name": "X-Request-ID",
            "in": "header",
            "required": true,
            "description": "UUID of the request message",
            "schema": {
              "type": "string",
              "format": "uuid"
            }
          },
          {
            "name": "x-insurantid",
            "in": "header",
            "required": true,
            "description": "Health Record Identifier",
            "schema": {
              "type": "string",
              "pattern": "^[A-Z]{1}\\d{9}$"
            }
          },
          {
            "name": "x-useragent",
            "in": "header",
            "required": true,
            "description": "user agent information",
            "schema": {
              "type": "string",
              "pattern": "^[a-zA-Z0-9]{20}\\/[a-zA-Z0-9\\-\\.]{1,15}$"
            }
          },
          {
            "name": "id",
            "in": "path",
            "required": true,
            "schema": {
              "type": "string"
            },
            "description": "Resource ID"
          },
          {
            "name": "_format",
            "in": "query",
            "required": false,
            "description": "Specifies the return format",
            "schema": {
              "type": "string",
              "enum": [
                "application/fhir+json",
                "application/fhir+xml"
              ]
            }
          },
          {
            "name": "_count",
            "in": "query",
            "required": false,
            "description": "With _count, the client can specify the maximum number of elements to be included on one page of the response. This means the Medication Service limits the result set to this maximum specified number. If no value for _count is provided, the default value set is 25.",
            "schema": {
              "type": "string"
            }
          },
          {
            "name": "_offset",
            "in": "query",
            "required": false,
            "description": "This URL parameter indicates the (zero-based) offset of the first returned element in the collection. If no value for _offset is provided, the default value set is 0.",
            "schema": {
              "type": "integer"
            }
          },
          {
            "name": "_total",
            "in": "query",
            "required": false,
            "description": "This parameter controls whether and how the AuditEvent Service returns the total number of search results.",
            "schema": {
              "type": "string"
            }
          }
        ],
        "responses": {
          "200": {
            "description": "History retrieved",
            "content": {
              "application/fhir+json": {
                "schema": {
                  "type": "object"
                }
              },
              "application/fhir+xml": {
                "schema": {
                  "type": "object"
                }
              }
            }
          },
          "400": {
            "description": "Invalid request"
          },
          "404": {
            "description": "Health record is in state UNKNOWN or INITIALIZED"
          },
          "403": {
            "description": "Device registration does not exist"
          },
          "409": {
            "description": "Health record is in state SUSPENDED"
          },
          "500": {
            "description": "Any other error"
          }
        }
      }
    },
    "/Patient/_history": {
      "get": {
        "summary": "History for all Patient",
        "tags": [
          "Patient"
        ],
        "parameters": [
          {
            "name": "X-Request-ID",
            "in": "header",
            "required": true,
            "description": "UUID of the request message",
            "schema": {
              "type": "string",
              "format": "uuid"
            }
          },
          {
            "name": "x-insurantid",
            "in": "header",
            "required": true,
            "description": "Health Record Identifier",
            "schema": {
              "type": "string",
              "pattern": "^[A-Z]{1}\\d{9}$"
            }
          },
          {
            "name": "x-useragent",
            "in": "header",
            "required": true,
            "description": "user agent information",
            "schema": {
              "type": "string",
              "pattern": "^[a-zA-Z0-9]{20}\\/[a-zA-Z0-9\\-\\.]{1,15}$"
            }
          },
          {
            "name": "_format",
            "in": "query",
            "required": false,
            "description": "Specifies the return format",
            "schema": {
              "type": "string",
              "enum": [
                "application/fhir+json",
                "application/fhir+xml"
              ]
            }
          },
          {
            "name": "_count",
            "in": "query",
            "required": false,
            "description": "With _count, the client can specify the maximum number of elements to be included on one page of the response. This means the Medication Service limits the result set to this maximum specified number. If no value for _count is provided, the default value set is 25.",
            "schema": {
              "type": "string"
            }
          },
          {
            "name": "_offset",
            "in": "query",
            "required": false,
            "description": "This URL parameter indicates the (zero-based) offset of the first returned element in the collection. If no value for _offset is provided, the default value set is 0.",
            "schema": {
              "type": "integer"
            }
          },
          {
            "name": "_total",
            "in": "query",
            "required": false,
            "description": "This parameter controls whether and how the AuditEvent Service returns the total number of search results.",
            "schema": {
              "type": "string"
            }
          }
        ],
        "responses": {
          "200": {
            "description": "History for type retrieved",
            "content": {
              "application/fhir+json": {
                "schema": {
                  "type": "object"
                }
              },
              "application/fhir+xml": {
                "schema": {
                  "type": "object"
                }
              }
            }
          },
          "400": {
            "description": "Invalid request"
          },
          "404": {
            "description": "Health record is in state UNKNOWN or INITIALIZED"
          },
          "403": {
            "description": "Device registration does not exist"
          },
          "409": {
            "description": "Health record is in state SUSPENDED"
          },
          "500": {
            "description": "Any other error"
          }
        }
      }
    },
    "/epa/medication/api/v1/fhir/metadata": {
      "get": {
        "responses": {
          "200": {
            "description": "This functionality ensures that a call to /metadata returns the FHIR CapabilityStatement.",
            "content": {
              "application/fhir+json": {
                "schema": {
                  "type": "object"
                }
              },
              "application/fhir+xml": {
                "schema": {
                  "type": "object"
                }
              }
            }
          },
          "403": {
            "description": "Device registration does not exist"
          },
          "404": {
            "description": "Health record is in state UNKNOWN or INITIALIZED"
          },
          "409": {
            "description": "Health record is in state SUSPENDED"
          },
          "500": {
            "description": "Any other error"
          }
        },
        "parameters": [
          {
            "name": "X-Request-ID",
            "in": "header",
            "required": true,
            "description": "UUID of the request message",
            "schema": {
              "type": "string",
              "format": "uuid"
            }
          },
          {
            "name": "x-insurantid",
            "in": "header",
            "required": true,
            "description": "Health Record Identifier",
            "schema": {
              "type": "string",
              "pattern": "^[A-Z]{1}\\d{9}$"
            }
          },
          {
            "name": "x-useragent",
            "in": "header",
            "required": true,
            "description": "user agent information",
            "schema": {
              "type": "string",
              "pattern": "^[a-zA-Z0-9]{20}\\/[a-zA-Z0-9\\-\\.]{1,15}$"
            }
          }
        ]
      }
    },
    "/epa/medication/api/v1/fhir/$medication-list": {
      "get": {
        "operationId": "getMedicationList_MedicationSvc",
        "tags": [
          "Operations"
        ],
        "parameters": [
          {
            "name": "X-Request-ID",
            "in": "header",
            "required": true,
            "description": "UUID of the request message",
            "schema": {
              "type": "string",
              "format": "uuid"
            }
          },
          {
            "name": "x-insurantid",
            "in": "header",
            "required": true,
            "description": "Health Record Identifier",
            "schema": {
              "type": "string",
              "pattern": "^[A-Z]{1}\\d{9}$"
            }
          },
          {
            "name": "x-useragent",
            "in": "header",
            "required": true,
            "description": "user agent information",
            "schema": {
              "type": "string",
              "pattern": "^[a-zA-Z0-9]{20}\\/[a-zA-Z0-9\\-\\.]{1,15}$"
            }
          },
          {
            "name": "date",
            "in": "query",
            "required": false,
            "schema": {
              "type": "string",
              "format": "date"
            },
            "description": "Limit the search to this date. Can specify upper or lower limits and periods by providing an upper and a lower limit."
          },
          {
            "name": "_count",
            "in": "query",
            "required": false,
            "description": "Limit the result bundle to this many entries. To get more entries request the next page.",
            "schema": {
              "type": "string"
            }
          },
          {
            "name": "_offset",
            "in": "query",
            "required": false,
            "description": "Defines the offset of the first entry in the collection.",
            "schema": {
              "type": "integer"
            }
          },
          {
            "name": "_format",
            "in": "query",
            "required": false,
            "description": "Specifies the return format",
            "schema": {
              "type": "string",
              "enum": [
                "application/fhir+json",
                "application/fhir+xml"
              ]
            }
          }
        ],
        "responses": {
          "200": {
            "description": "History retrieved",
            "content": {
              "application/fhir+json": {
                "schema": {
                  "type": "object"
                }
              },
              "application/fhir+xml": {
                "schema": {
                  "type": "object"
                }
              }
            }
          },
          "403": {
            "description": "Device registration does not exist"
          },
          "404": {
            "description": "Health record is in state UNKNOWN or INITIALIZED"
          },
          "409": {
            "description": "Health record is in state SUSPENDED"
          },
          "500": {
            "description": "Any other error"
          }
        }
      }
    },
    "/epa/medication/api/v1/fhir/$provide-prescription-erp": {
      "post": {
        "operationId": "providePrescription_MedicationSvc",
        "tags": [
          "Operations"
        ],
        "requestBody": {
          "required": true,
          "content": {
            "application/fhir+json": {
              "schema": {
                "type": "object"
              }
            },
            "application/fhir+xml": {
              "schema": {
                "type": "object"
              }
            }
          }
        },
        "responses": {
          "200": {
            "description": "EPAOpRxPrescriptionERPOutputParameters",
            "content": {
              "application/fhir+json": {
                "schema": {
                  "type": "object"
                }
              },
              "application/fhir+xml": {
                "schema": {
                  "type": "object"
                }
              }
            }
          },
          "403": {
            "description": "Device registration does not exist"
          },
          "404": {
            "description": "Health record is in state UNKNOWN or INITIALIZED"
          },
          "409": {
            "description": "Health record is in state SUSPENDED"
          },
          "500": {
            "description": "Any other error"
          }
        },
        "parameters": [
          {
            "name": "X-Request-ID",
            "in": "header",
            "required": true,
            "description": "UUID of the request message",
            "schema": {
              "type": "string",
              "format": "uuid"
            }
          },
          {
            "name": "x-insurantid",
            "in": "header",
            "required": true,
            "description": "Health Record Identifier",
            "schema": {
              "type": "string",
              "pattern": "^[A-Z]{1}\\d{9}$"
            }
          },
          {
            "name": "x-useragent",
            "in": "header",
            "required": true,
            "description": "user agent information",
            "schema": {
              "type": "string",
              "pattern": "^[a-zA-Z0-9]{20}\\/[a-zA-Z0-9\\-\\.]{1,15}$"
            }
          }
        ]
      }
    },
    "/epa/medication/api/v1/fhir/$provide-dispensation-erp": {
      "post": {
        "operationId": "provideDispensation_MedicationSvc",
        "tags": [
          "Operations"
        ],
        "requestBody": {
          "required": true,
          "content": {
            "application/fhir+json": {
              "schema": {
                "type": "object"
              }
            },
            "application/fhir+xml": {
              "schema": {
                "type": "object"
              }
            }
          }
        },
        "responses": {
          "200": {
            "description": "EPAOpRxDispensationERPOutputParameters",
            "content": {
              "application/fhir+json": {
                "schema": {
                  "type": "object"
                }
              },
              "application/fhir+xml": {
                "schema": {
                  "type": "object"
                }
              }
            }
          },
          "403": {
            "description": "Device registration does not exist"
          },
          "404": {
            "description": "Health record is in state UNKNOWN or INITIALIZED"
          },
          "409": {
            "description": "Health record is in state SUSPENDED"
          },
          "500": {
            "description": "Any other error"
          }
        },
        "parameters": [
          {
            "name": "X-Request-ID",
            "in": "header",
            "required": true,
            "description": "UUID of the request message",
            "schema": {
              "type": "string",
              "format": "uuid"
            }
          },
          {
            "name": "x-insurantid",
            "in": "header",
            "required": true,
            "description": "Health Record Identifier",
            "schema": {
              "type": "string",
              "pattern": "^[A-Z]{1}\\d{9}$"
            }
          },
          {
            "name": "x-useragent",
            "in": "header",
            "required": true,
            "description": "user agent information",
            "schema": {
              "type": "string",
              "pattern": "^[a-zA-Z0-9]{20}\\/[a-zA-Z0-9\\-\\.]{1,15}$"
            }
          }
        ]
      }
    },
    "/epa/medication/api/v1/fhir/$cancel-prescription-erp": {
      "post": {
        "operationId": "cancelPrescription_MedicationSvc",
        "tags": [
          "Operations"
        ],
        "requestBody": {
          "required": true,
          "content": {
            "application/fhir+json": {
              "schema": {
                "type": "object"
              }
            },
            "application/fhir+xml": {
              "schema": {
                "type": "object"
              }
            }
          }
        },
        "responses": {
          "200": {
            "description": "EPAOpRxPrescriptionERPOutputParameters",
            "content": {
              "application/fhir+json": {
                "schema": {
                  "type": "object"
                }
              },
              "application/fhir+xml": {
                "schema": {
                  "type": "object"
                }
              }
            }
          },
          "403": {
            "description": "Device registration does not exist"
          },
          "404": {
            "description": "Health record is in state UNKNOWN or INITIALIZED"
          },
          "409": {
            "description": "Health record is in state SUSPENDED"
          },
          "500": {
            "description": "Any other error"
          }
        },
        "parameters": [
          {
            "name": "X-Request-ID",
            "in": "header",
            "required": true,
            "description": "UUID of the request message",
            "schema": {
              "type": "string",
              "format": "uuid"
            }
          },
          {
            "name": "x-insurantid",
            "in": "header",
            "required": true,
            "description": "Health Record Identifier",
            "schema": {
              "type": "string",
              "pattern": "^[A-Z]{1}\\d{9}$"
            }
          },
          {
            "name": "x-useragent",
            "in": "header",
            "required": true,
            "description": "user agent information",
            "schema": {
              "type": "string",
              "pattern": "^[a-zA-Z0-9]{20}\\/[a-zA-Z0-9\\-\\.]{1,15}$"
            }
          }
        ]
      }
    },
    "/epa/medication/api/v1/fhir/$cancel-dispensation-erp": {
      "post": {
        "operationId": "cancelDispensation_MedicationSvc",
        "tags": [
          "Operations"
        ],
        "requestBody": {
          "required": true,
          "content": {
            "application/fhir+json": {
              "schema": {
                "type": "object"
              }
            },
            "application/fhir+xml": {
              "schema": {
                "type": "object"
              }
            }
          }
        },
        "responses": {
          "200": {
            "description": "EPAOpRxDispensationERPOutputParameters",
            "content": {
              "application/fhir+json": {
                "schema": {
                  "type": "object"
                }
              },
              "application/fhir+xml": {
                "schema": {
                  "type": "object"
                }
              }
            }
          },
          "403": {
            "description": "Device registration does not exist"
          },
          "404": {
            "description": "Health record is in state UNKNOWN or INITIALIZED"
          },
          "409": {
            "description": "Health record is in state SUSPENDED"
          },
          "500": {
            "description": "Any other error"
          }
        },
        "parameters": [
          {
            "name": "X-Request-ID",
            "in": "header",
            "required": true,
            "description": "UUID of the request message",
            "schema": {
              "type": "string",
              "format": "uuid"
            }
          },
          {
            "name": "x-insurantid",
            "in": "header",
            "required": true,
            "description": "Health Record Identifier",
            "schema": {
              "type": "string",
              "pattern": "^[A-Z]{1}\\d{9}$"
            }
          },
          {
            "name": "x-useragent",
            "in": "header",
            "required": true,
            "description": "user agent information",
            "schema": {
              "type": "string",
              "pattern": "^[a-zA-Z0-9]{20}\\/[a-zA-Z0-9\\-\\.]{1,15}$"
            }
          }
        ]
      }
    },
    "/epa/medication/render/v1/eml/xhtml": {
      "get": {
        "operationId": "renderEMLAsHTML",
        "tags": [
          "Render"
        ],
        "responses": {
          "200": {
            "description": "OK",
            "content": {
              "text/html": {
                "schema": {
                  "type": "string"
                }
              }
            }
          },
          "403": {
            "description": "Device registration does not exist"
          },
          "404": {
            "description": "Health record is in state UNKNOWN or INITIALIZED"
          },
          "409": {
            "description": "Health record is in state SUSPENDED"
          },
          "500": {
            "description": "Any other error"
          }
        },
        "parameters": [
          {
            "name": "X-Request-ID",
            "in": "header",
            "required": true,
            "description": "UUID of the request message",
            "schema": {
              "type": "string",
              "format": "uuid"
            }
          },
          {
            "name": "x-insurantid",
            "in": "header",
            "required": true,
            "description": "Health Record Identifier",
            "schema": {
              "type": "string",
              "pattern": "^[A-Z]{1}\\d{9}$"
            }
          },
          {
            "name": "x-useragent",
            "in": "header",
            "required": true,
            "description": "user agent information",
            "schema": {
              "type": "string",
              "pattern": "^[a-zA-Z0-9]{20}\\/[a-zA-Z0-9\\-\\.]{1,15}$"
            }
          }
        ]
      }
    },
    "/epa/medication/render/v1/eml/pdf": {
      "get": {
        "operationId": "renderEMLAsPDF",
        "tags": [
          "Render"
        ],
        "responses": {
          "200": {
            "description": "OK",
            "content": {
              "application/pdf": {
                "schema": {
                  "type": "string",
                  "format": "binary"
                }
              }
            }
          },
          "403": {
            "description": "Device registration does not exist"
          },
          "404": {
            "description": "Health record is in state UNKNOWN or INITIALIZED"
          },
          "409": {
            "description": "Health record is in state SUSPENDED"
          },
          "500": {
            "description": "Any other error"
          }
        },
        "parameters": [
          {
            "name": "X-Request-ID",
            "in": "header",
            "required": true,
            "description": "UUID of the request message",
            "schema": {
              "type": "string",
              "format": "uuid"
            }
          },
          {
            "name": "x-insurantid",
            "in": "header",
            "required": true,
            "description": "Health Record Identifier",
            "schema": {
              "type": "string",
              "pattern": "^[A-Z]{1}\\d{9}$"
            }
          },
          {
            "name": "x-useragent",
            "in": "header",
            "required": true,
            "description": "user agent information",
            "schema": {
              "type": "string",
              "pattern": "^[a-zA-Z0-9]{20}\\/[a-zA-Z0-9\\-\\.]{1,15}$"
            }
          }
        ]
      }
    }
  },
  "components": {
    "responses": {},
    "headers": {}
  }
}