{
  "resourceType": "OperationDefinition",
  "id": "update-emp-entry-op",
  "meta": {
    "profile": [
      "https://gematik.de/fhir/ti/StructureDefinition/ti-operationdefinition"
    ]
  },
  "url": "https://gematik.de/fhir/epa-medication/OperationDefinition/update-emp-entry-op",
  "title": "eMP-Eintrag aktualisieren",
  "description": "Diese Operation dient der gezielten Aktualisierung eines bestehenden Medikations-Eintrags im elektronischen Medikationsplan (eMP).",
  "extension": [
    {
      "url": "https://gematik.de/fhir/ti/StructureDefinition/extension-http-method",
      "valueCode": "POST"
    }
  ],
  "version": "1.2.0",
  "status": "active",
  "publisher": "gematik GmbH",
  "date": "2025-07-15",
  "kind": "operation",
  "name": "updateEMPEntry_MedicationSvc",
  "code": "update-emp-entry",
  "affectsState": true,
  "system": true,
  "type": false,
  "instance": false
}
